machado/__init__.py
machado/apps.py
machado/decorators.py
machado/forms.py
machado/models.py
machado/search_indexes.py
machado/settings.py
machado/urls.py
machado/api/__init__.py
machado/api/serializers.py
machado/api/urls.py
machado/api/views.py
machado/loaders/__init__.py
machado/loaders/analysis.py
machado/loaders/assay.py
machado/loaders/biomaterial.py
machado/loaders/common.py
machado/loaders/exceptions.py
machado/loaders/feature.py
machado/loaders/ontology.py
machado/loaders/organism.py
machado/loaders/phylotree.py
machado/loaders/project.py
machado/loaders/publication.py
machado/loaders/sequence.py
machado/loaders/similarity.py
machado/loaders/treatment.py
machado/management/__init__.py
machado/management/commands/__init__.py
machado/management/commands/insert_organism.py
machado/management/commands/load_coexpression_clusters.py
machado/management/commands/load_coexpression_pairs.py
machado/management/commands/load_fasta.py
machado/management/commands/load_feature_annotation.py
machado/management/commands/load_feature_dbxrefs.py
machado/management/commands/load_feature_publication.py
machado/management/commands/load_feature_sequence.py
machado/management/commands/load_gene_ontology.py
machado/management/commands/load_gff.py
machado/management/commands/load_organism.py
machado/management/commands/load_organism_publication.py
machado/management/commands/load_orthomcl.py
machado/management/commands/load_phylotree.py
machado/management/commands/load_publication.py
machado/management/commands/load_relations_ontology.py
machado/management/commands/load_rnaseq_data.py
machado/management/commands/load_rnaseq_info.py
machado/management/commands/load_sequence_ontology.py
machado/management/commands/load_similarity.py
machado/management/commands/load_similarity_matches.py
machado/management/commands/remove_analysis.py
machado/management/commands/remove_feature_annotation.py
machado/management/commands/remove_file.py
machado/management/commands/remove_ontology.py
machado-0.3.0.dist-info/LICENSE.txt
machado-0.3.0.dist-info/METADATA
machado-0.3.0.dist-info/WHEEL
machado-0.3.0.dist-info/top_level.txt
machado-0.3.0.dist-info/RECORD
