Metadata-Version: 2.1
Name: machado
Version: 0.3.0
Summary: This library provides users with a framework to store, search and visualize biological data.
Home-page: https://github.com/lmb-embrapa/machado
Author: LMB
Author-email: UNKNOWN
License: GPL License
Platform: UNKNOWN
Classifier: Environment :: Console
Classifier: Framework :: Django :: 2.2
Classifier: License :: OSI Approved :: GNU General Public License v3 (GPLv3)
Classifier: Programming Language :: Python :: 3
Requires-Dist: django (==2.2.13)
Requires-Dist: psycopg2-binary (==2.8.5)
Requires-Dist: biopython (==1.76)
Requires-Dist: obonet (==0.2.5)
Requires-Dist: tqdm (==4.45.0)
Requires-Dist: typing (==3.7.4.1)
Requires-Dist: bibtexparser (==1.1.0)
Requires-Dist: djangorestframework (==3.11.0)
Requires-Dist: drf-yasg (==1.17.1)
Requires-Dist: drf-nested-routers (==0.91)
Requires-Dist: pysam (==0.15.2)
